{"skeleton":{"hash":"H7oYUkrGDyVEqP1hCHULz5DfKmw","spine":"3.7.93","width":2144.66,"height":1261.36},"bones":[{"name":"root"},{"name":"bone","parent":"root","x":1.68,"y":-577.54},{"name":"bone7","parent":"root","x":-302.41,"y":-1.19},{"name":"bone2","parent":"bone7","x":4.10,"y":23.39},{"name":"bone3","parent":"bone2","length":136.98,"x":756.53,"y":-31.06,"rotation":89.26,"shearX":-1.35},{"name":"bone4","parent":"bone3","length":256.36,"x":-1.61,"y":1.57,"rotation":-141.32},{"name":"bone5","parent":"bone2","length":136.98,"x":-404.99,"y":250.31,"rotation":89.26,"scaleX":0.82586,"scaleY":0.82586,"shearX":-4.60},{"name":"bone6","parent":"bone5","length":256.36,"x":-1.61,"y":1.57,"rotation":-141.32}],"slots":[{"name":"back","bone":"bone","attachment":"back"},{"name":"back2","bone":"bone","attachment":"back"},{"name":"screen","bone":"bone","color":"ffffff76","attachment":"screen","blend":"additive"},{"name":"p1","bone":"bone4","color":"ffffffab","attachment":"p1"},{"name":"p2","bone":"bone6","color":"ffffffa9","attachment":"p1"},{"name":"a1","bone":"bone2","attachment":"a1"},{"name":"a2","bone":"bone2","attachment":"a1"},{"name":"l4","bone":"bone2","attachment":"l4"},{"name":"l3","bone":"bone2","attachment":"l3"},{"name":"l2","bone":"bone2","attachment":"l2"},{"name":"l1","bone":"bone","attachment":"l1","blend":"additive"},{"name":"l5","bone":"bone","attachment":"l1","blend":"additive"}],"skins":{"default":{"a1":{"a1":{"x":69.32,"y":146.30,"width":1444,"height":745}},"a2":{"a1":{"path":"a2","x":69.32,"y":146.30,"scaleX":2,"scaleY":2,"width":722,"height":373}},"back":{"back":{"x":-1.68,"y":577.54,"scaleX":2,"scaleY":2,"width":961,"height":541}},"back2":{"back":{"path":"back2","x":-1.68,"y":577.54,"scaleX":4,"scaleY":4,"width":481,"height":271}},"l1":{"l1":{"x":-9.18,"y":581.04,"scaleX":2,"scaleY":2,"width":954,"height":476}},"l2":{"l2":{"x":676.32,"y":13.80,"scaleX":2,"scaleY":2,"width":479,"height":100}},"l3":{"l3":{"x":23.82,"y":41.80,"scaleX":2,"scaleY":2,"width":188,"height":52}},"l4":{"l4":{"x":-124.68,"y":396.30,"scaleX":2,"scaleY":2,"width":538,"height":101}},"l5":{"l1":{"x":-9.18,"y":581.04,"scaleX":-1.84,"scaleY":-1.94,"width":954,"height":476}},"p1":{"p1":{"x":-12.01,"y":-4.10,"rotation":52.06,"scaleX":2,"scaleY":2,"width":513,"height":538}},"p2":{"p1":{"x":-12.01,"y":-4.10,"rotation":52.06,"scaleX":2,"scaleY":2,"width":513,"height":538}},"screen":{"screen":{"x":-1.68,"y":291.30,"scaleX":2,"scaleY":2,"width":961,"height":254}}}},"animations":{"BASE":{"slots":{"a1":{"color":[{"time":0,"color":"ffffffff","curve":"stepped"},{"time":2.67,"color":"ffffffff","curve":"stepped"},{"time":8,"color":"ffffffff","curve":"stepped"},{"time":11,"color":"ffffffff","curve":"stepped"},{"time":12,"color":"ffffffff"}]},"a2":{"color":[{"time":0,"color":"ffffff00"},{"time":3.33,"color":"ffffffff"},{"time":6,"color":"ffffff00"},{"time":10.03,"color":"adadadff"},{"time":12,"color":"ffffff00"}]},"back2":{"color":[{"time":0,"color":"ffffffff"},{"time":3,"color":"ffffff00"},{"time":6,"color":"ffffffff"},{"time":9,"color":"ffffff00"},{"time":12,"color":"ffffffff"}]},"l1":{"color":[{"time":0,"color":"ffffffff"},{"time":0.33333,"color":"ffffff00","curve":"stepped"},{"time":0.66667,"color":"ffffff00"},{"time":1,"color":"ffffffff","curve":"stepped"},{"time":1.33,"color":"ffffffff"},{"time":1.67,"color":"ffffff00","curve":"stepped"},{"time":2.33,"color":"ffffff00"},{"time":2.67,"color":"ffffffff","curve":"stepped"},{"time":3,"color":"ffffffff"},{"time":3.33,"color":"ffffff00","curve":"stepped"},{"time":3.67,"color":"ffffff00"},{"time":4,"color":"ffffffff","curve":"stepped"},{"time":4.33,"color":"ffffffff"},{"time":4.67,"color":"ffffff00","curve":"stepped"},{"time":5.33,"color":"ffffff00"},{"time":5.67,"color":"ffffffff","curve":"stepped"},{"time":6,"color":"ffffffff"},{"time":6.33,"color":"ffffff00","curve":"stepped"},{"time":6.67,"color":"ffffff00"},{"time":7,"color":"ffffffff","curve":"stepped"},{"time":7.33,"color":"ffffffff"},{"time":7.67,"color":"ffffff00","curve":"stepped"},{"time":8.33,"color":"ffffff00"},{"time":8.67,"color":"ffffffff","curve":"stepped"},{"time":9,"color":"ffffffff"},{"time":9.33,"color":"ffffff00","curve":"stepped"},{"time":9.67,"color":"ffffff00"},{"time":10,"color":"ffffffff","curve":"stepped"},{"time":10.33,"color":"ffffffff"},{"time":10.67,"color":"ffffff00","curve":"stepped"},{"time":11.33,"color":"ffffff00"},{"time":11.67,"color":"ffffffff","curve":"stepped"},{"time":12,"color":"ffffffff"}]},"l2":{"color":[{"time":0,"color":"ffffff00","curve":"stepped"},{"time":0.26667,"color":"ffffff00"},{"time":0.76667,"color":"ffffffff","curve":"stepped"},{"time":1.43,"color":"ffffffff"},{"time":1.93,"color":"ffffff00","curve":"stepped"},{"time":2.30,"color":"ffffff00"},{"time":2.80,"color":"ffffffff","curve":"stepped"},{"time":3.47,"color":"ffffffff"},{"time":3.97,"color":"ffffff00","curve":"stepped"},{"time":4.33,"color":"ffffff00"},{"time":4.83,"color":"ffffffff","curve":"stepped"},{"time":5.50,"color":"ffffffff"},{"time":6,"color":"ffffff00","curve":"stepped"},{"time":6.27,"color":"ffffff00"},{"time":6.77,"color":"ffffffff","curve":"stepped"},{"time":7.43,"color":"ffffffff"},{"time":7.93,"color":"ffffff00","curve":"stepped"},{"time":8.30,"color":"ffffff00"},{"time":8.80,"color":"ffffffff","curve":"stepped"},{"time":9.47,"color":"ffffffff"},{"time":9.97,"color":"ffffff00","curve":"stepped"},{"time":10.33,"color":"ffffff00"},{"time":10.83,"color":"ffffffff","curve":"stepped"},{"time":11.50,"color":"ffffffff"},{"time":12,"color":"ffffff00"}]},"l3":{"color":[{"time":0,"color":"ffffff00"},{"time":0.50000,"color":"ffffffff","curve":"stepped"},{"time":1.17,"color":"ffffffff"},{"time":1.67,"color":"ffffff00","curve":"stepped"},{"time":3,"color":"ffffff00"},{"time":3.50,"color":"ffffffff","curve":"stepped"},{"time":4.17,"color":"ffffffff"},{"time":4.67,"color":"ffffff00","curve":"stepped"},{"time":6,"color":"ffffff00"},{"time":6.50,"color":"ffffffff","curve":"stepped"},{"time":7.17,"color":"ffffffff"},{"time":7.67,"color":"ffffff00","curve":"stepped"},{"time":9,"color":"ffffff00"},{"time":9.50,"color":"ffffffff","curve":"stepped"},{"time":10.17,"color":"ffffffff"},{"time":10.67,"color":"ffffff00","curve":"stepped"},{"time":12,"color":"ffffff00"}]},"l4":{"color":[{"time":0,"color":"ffffff00","curve":"stepped"},{"time":0.26667,"color":"ffffff00"},{"time":0.53333,"color":"ffffffff","curve":"stepped"},{"time":0.90000,"color":"ffffffff"},{"time":1.17,"color":"ffffff00","curve":"stepped"},{"time":1.87,"color":"ffffff00"},{"time":2.13,"color":"ffffffff","curve":"stepped"},{"time":2.50,"color":"ffffffff"},{"time":2.77,"color":"ffffff00","curve":"stepped"},{"time":3.30,"color":"ffffff00"},{"time":3.57,"color":"ffffffff","curve":"stepped"},{"time":3.93,"color":"ffffffff"},{"time":4.20,"color":"ffffff00","curve":"stepped"},{"time":4.83,"color":"ffffff00"},{"time":5.10,"color":"ffffffff","curve":"stepped"},{"time":5.47,"color":"ffffffff"},{"time":5.73,"color":"ffffff00","curve":"stepped"},{"time":6,"color":"ffffff00","curve":"stepped"},{"time":6.27,"color":"ffffff00"},{"time":6.53,"color":"ffffffff","curve":"stepped"},{"time":6.90,"color":"ffffffff"},{"time":7.17,"color":"ffffff00","curve":"stepped"},{"time":7.87,"color":"ffffff00"},{"time":8.13,"color":"ffffffff","curve":"stepped"},{"time":8.50,"color":"ffffffff"},{"time":8.77,"color":"ffffff00","curve":"stepped"},{"time":9.30,"color":"ffffff00"},{"time":9.57,"color":"ffffffff","curve":"stepped"},{"time":9.93,"color":"ffffffff"},{"time":10.20,"color":"ffffff00","curve":"stepped"},{"time":10.83,"color":"ffffff00"},{"time":11.10,"color":"ffffffff","curve":"stepped"},{"time":11.47,"color":"ffffffff"},{"time":11.73,"color":"ffffff00","curve":"stepped"},{"time":12,"color":"ffffff00"}]},"l5":{"color":[{"time":0,"color":"ffffffff"},{"time":0.46667,"color":"ffffff00","curve":"stepped"},{"time":0.96667,"color":"ffffff00"},{"time":1.43,"color":"ffffffff","curve":"stepped"},{"time":1.93,"color":"ffffffff"},{"time":2.40,"color":"ffffff00","curve":"stepped"},{"time":3.37,"color":"ffffff00"},{"time":3.83,"color":"ffffffff","curve":"stepped"},{"time":4.30,"color":"ffffffff"},{"time":4.80,"color":"ffffff00","curve":"stepped"},{"time":5.27,"color":"ffffff00"},{"time":5.77,"color":"ffffffff","curve":"stepped"},{"time":6.23,"color":"ffffffff"},{"time":6.70,"color":"ffffff00","curve":"stepped"},{"time":7.67,"color":"ffffff00"},{"time":8.13,"color":"ffffffff","curve":"stepped"},{"time":8.63,"color":"ffffffff"},{"time":9.10,"color":"ffffff00","curve":"stepped"},{"time":9.60,"color":"ffffff00"},{"time":10.07,"color":"ffffffff","curve":"stepped"},{"time":10.53,"color":"ffffffff"},{"time":11.03,"color":"ffffff00","curve":"stepped"},{"time":11.50,"color":"ffffff00"},{"time":12,"color":"ffffffff"}]},"screen":{"color":[{"time":0,"color":"ffffff40"},{"time":0.83333,"color":"ffffff83","curve":"stepped"},{"time":1.67,"color":"ffffff83"},{"time":2.50,"color":"ffffff40","curve":"stepped"},{"time":3.13,"color":"ffffff40"},{"time":3.97,"color":"ffffff83","curve":"stepped"},{"time":4.80,"color":"ffffff83"},{"time":5.63,"color":"ffffff40","curve":"stepped"},{"time":6,"color":"ffffff40"},{"time":6.83,"color":"ffffff83","curve":"stepped"},{"time":7.67,"color":"ffffff83"},{"time":8.50,"color":"ffffff40","curve":"stepped"},{"time":9.13,"color":"ffffff40"},{"time":9.97,"color":"ffffff83","curve":"stepped"},{"time":10.80,"color":"ffffff83"},{"time":11.63,"color":"ffffff40","curve":"stepped"},{"time":12,"color":"ffffff40"}]}},"bones":{"bone":{"rotate":[{"time":0,"angle":0,"curve":"stepped"},{"time":12,"angle":0}],"translate":[{"time":0,"x":0,"y":0,"curve":[0.25000,0,0.75000,1]},{"time":6,"x":-6.68,"y":8.91,"curve":[0.25000,0,0.75000,1]},{"time":12,"x":0,"y":0}],"scale":[{"time":0,"x":1,"y":1,"curve":[0.25000,0,0.75000,1]},{"time":6,"x":1.01,"y":1.01,"curve":[0.25000,0,0.75000,1]},{"time":12,"x":1,"y":1}]},"bone2":{"rotate":[{"time":0,"angle":0.09366,"curve":[0.30791,0.25225,0.65819,0.63964]},{"time":2,"angle":0.35149,"curve":[0.37931,0.52632,0.74608,1]},{"time":4.67,"angle":0.61299,"curve":[0.25000,0,0.75000,1]},{"time":10.67,"angle":0,"curve":[0.28028,0,0.62284,0.39130]},{"time":12,"angle":0.09366}],"translate":[{"time":0,"x":0,"y":-7.77,"curve":[0.38235,0.57143,0.73529,1]},{"time":2,"x":-18.40,"y":-0.11291,"curve":[0.25000,0,0.75000,1]},{"time":8,"x":0,"y":-27.38,"curve":[0.24324,0,0.64865,0.60000]},{"time":12,"x":0,"y":-7.77}],"scale":[{"time":0,"x":1.01,"y":1.01,"curve":[0.38235,0.57143,0.73529,1]},{"time":2,"x":1,"y":1},{"time":8,"x":1.02,"y":1.02,"curve":[0.24324,0,0.64865,0.60000]},{"time":12,"x":1.01,"y":1.01}]},"bone3":{"rotate":[{"time":0,"angle":0,"curve":"stepped"},{"time":12,"angle":0}],"translate":[{"time":0,"x":0,"y":0,"curve":"stepped"},{"time":12,"x":0,"y":0}],"scale":[{"time":0,"x":1,"y":1,"curve":"stepped"},{"time":12,"x":1,"y":1}]},"bone4":{"rotate":[{"time":0,"angle":0},{"time":0.06667,"angle":240},{"time":0.13333,"angle":120},{"time":0.20000,"angle":0},{"time":0.26667,"angle":240},{"time":0.33333,"angle":120},{"time":0.40000,"angle":0},{"time":0.46667,"angle":240},{"time":0.53333,"angle":120},{"time":0.60000,"angle":0},{"time":0.66667,"angle":240},{"time":0.73333,"angle":120},{"time":0.80000,"angle":0},{"time":0.86667,"angle":240},{"time":0.93333,"angle":120},{"time":1,"angle":0},{"time":1.07,"angle":240},{"time":1.13,"angle":120},{"time":1.20,"angle":0},{"time":1.27,"angle":240},{"time":1.33,"angle":120},{"time":1.40,"angle":0},{"time":1.47,"angle":240},{"time":1.53,"angle":120},{"time":1.60,"angle":0},{"time":1.67,"angle":240},{"time":1.73,"angle":120},{"time":1.80,"angle":0},{"time":1.87,"angle":240},{"time":1.93,"angle":120},{"time":2,"angle":0},{"time":2.07,"angle":240},{"time":2.13,"angle":120},{"time":2.20,"angle":0},{"time":2.27,"angle":240},{"time":2.33,"angle":120},{"time":2.40,"angle":0},{"time":2.47,"angle":240},{"time":2.53,"angle":120},{"time":2.60,"angle":0},{"time":2.67,"angle":240},{"time":2.73,"angle":120},{"time":2.80,"angle":0},{"time":2.87,"angle":240},{"time":2.93,"angle":120},{"time":3,"angle":0},{"time":3.07,"angle":240},{"time":3.13,"angle":120},{"time":3.20,"angle":0},{"time":3.27,"angle":240},{"time":3.33,"angle":120},{"time":3.40,"angle":0},{"time":3.47,"angle":240},{"time":3.53,"angle":120},{"time":3.60,"angle":0},{"time":3.67,"angle":240},{"time":3.73,"angle":120},{"time":3.80,"angle":0},{"time":3.87,"angle":240},{"time":3.93,"angle":120},{"time":4,"angle":0},{"time":4.07,"angle":240},{"time":4.13,"angle":120},{"time":4.20,"angle":0},{"time":4.27,"angle":240},{"time":4.33,"angle":120},{"time":4.40,"angle":0},{"time":4.47,"angle":240},{"time":4.53,"angle":120},{"time":4.60,"angle":0},{"time":4.67,"angle":240},{"time":4.73,"angle":120},{"time":4.80,"angle":0},{"time":4.87,"angle":240},{"time":4.93,"angle":120},{"time":5,"angle":0},{"time":5.07,"angle":240},{"time":5.13,"angle":120},{"time":5.20,"angle":0},{"time":5.27,"angle":240},{"time":5.33,"angle":120},{"time":5.40,"angle":0},{"time":5.47,"angle":240},{"time":5.53,"angle":120},{"time":5.60,"angle":0},{"time":5.67,"angle":240},{"time":5.73,"angle":120},{"time":5.80,"angle":0},{"time":5.87,"angle":240},{"time":5.93,"angle":120},{"time":6,"angle":0},{"time":6.07,"angle":240},{"time":6.13,"angle":120},{"time":6.20,"angle":0},{"time":6.27,"angle":240},{"time":6.33,"angle":120},{"time":6.40,"angle":0},{"time":6.47,"angle":240},{"time":6.53,"angle":120},{"time":6.60,"angle":0},{"time":6.67,"angle":240},{"time":6.73,"angle":120},{"time":6.80,"angle":0},{"time":6.87,"angle":240},{"time":6.93,"angle":120},{"time":7,"angle":0},{"time":7.07,"angle":240},{"time":7.13,"angle":120},{"time":7.20,"angle":0},{"time":7.27,"angle":240},{"time":7.33,"angle":120},{"time":7.40,"angle":0},{"time":7.47,"angle":240},{"time":7.53,"angle":120},{"time":7.60,"angle":0},{"time":7.67,"angle":240},{"time":7.73,"angle":120},{"time":7.80,"angle":0},{"time":7.87,"angle":240},{"time":7.93,"angle":120},{"time":8,"angle":0},{"time":8.07,"angle":240},{"time":8.13,"angle":120},{"time":8.20,"angle":0},{"time":8.27,"angle":240},{"time":8.33,"angle":120},{"time":8.40,"angle":0},{"time":8.47,"angle":240},{"time":8.53,"angle":120},{"time":8.60,"angle":0},{"time":8.67,"angle":240},{"time":8.73,"angle":120},{"time":8.80,"angle":0},{"time":8.87,"angle":240},{"time":8.93,"angle":120},{"time":9,"angle":0},{"time":9.07,"angle":240},{"time":9.13,"angle":120},{"time":9.20,"angle":0},{"time":9.27,"angle":240},{"time":9.33,"angle":120},{"time":9.40,"angle":0},{"time":9.47,"angle":240},{"time":9.53,"angle":120},{"time":9.60,"angle":0},{"time":9.67,"angle":240},{"time":9.73,"angle":120},{"time":9.80,"angle":0},{"time":9.87,"angle":240},{"time":9.93,"angle":120},{"time":10,"angle":0},{"time":10.07,"angle":240},{"time":10.13,"angle":120},{"time":10.20,"angle":0},{"time":10.27,"angle":240},{"time":10.33,"angle":120},{"time":10.40,"angle":0},{"time":10.47,"angle":240},{"time":10.53,"angle":120},{"time":10.60,"angle":0},{"time":10.67,"angle":240},{"time":10.73,"angle":120},{"time":10.80,"angle":0},{"time":10.87,"angle":240},{"time":10.93,"angle":120},{"time":11,"angle":0},{"time":11.07,"angle":240},{"time":11.13,"angle":120},{"time":11.20,"angle":0},{"time":11.27,"angle":240},{"time":11.33,"angle":120},{"time":11.40,"angle":0},{"time":11.47,"angle":240},{"time":11.53,"angle":120},{"time":11.60,"angle":0},{"time":11.67,"angle":240},{"time":11.73,"angle":120},{"time":11.80,"angle":0},{"time":11.87,"angle":240},{"time":11.93,"angle":120},{"time":12,"angle":0}],"translate":[{"time":0,"x":0,"y":0,"curve":"stepped"},{"time":12,"x":0,"y":0}],"scale":[{"time":0,"x":1,"y":1,"curve":"stepped"},{"time":12,"x":1,"y":1}]},"bone5":{"rotate":[{"time":0,"angle":0,"curve":"stepped"},{"time":12,"angle":0}],"translate":[{"time":0,"x":0,"y":0,"curve":"stepped"},{"time":12,"x":0,"y":0}],"scale":[{"time":0,"x":1,"y":1,"curve":"stepped"},{"time":12,"x":1,"y":1}]},"bone6":{"rotate":[{"time":0,"angle":0},{"time":0.06667,"angle":240},{"time":0.13333,"angle":120},{"time":0.20000,"angle":0},{"time":0.26667,"angle":240},{"time":0.33333,"angle":120},{"time":0.40000,"angle":0},{"time":0.46667,"angle":240},{"time":0.53333,"angle":120},{"time":0.60000,"angle":0},{"time":0.66667,"angle":240},{"time":0.73333,"angle":120},{"time":0.80000,"angle":0},{"time":0.86667,"angle":240},{"time":0.93333,"angle":120},{"time":1,"angle":0},{"time":1.07,"angle":240},{"time":1.13,"angle":120},{"time":1.20,"angle":0},{"time":1.27,"angle":240},{"time":1.33,"angle":120},{"time":1.40,"angle":0},{"time":1.47,"angle":240},{"time":1.53,"angle":120},{"time":1.60,"angle":0},{"time":1.67,"angle":240},{"time":1.73,"angle":120},{"time":1.80,"angle":0},{"time":1.87,"angle":240},{"time":1.93,"angle":120},{"time":2,"angle":0},{"time":2.07,"angle":240},{"time":2.13,"angle":120},{"time":2.20,"angle":0},{"time":2.27,"angle":240},{"time":2.33,"angle":120},{"time":2.40,"angle":0},{"time":2.47,"angle":240},{"time":2.53,"angle":120},{"time":2.60,"angle":0},{"time":2.67,"angle":240},{"time":2.73,"angle":120},{"time":2.80,"angle":0},{"time":2.87,"angle":240},{"time":2.93,"angle":120},{"time":3,"angle":0},{"time":3.07,"angle":240},{"time":3.13,"angle":120},{"time":3.20,"angle":0},{"time":3.27,"angle":240},{"time":3.33,"angle":120},{"time":3.40,"angle":0},{"time":3.47,"angle":240},{"time":3.53,"angle":120},{"time":3.60,"angle":0},{"time":3.67,"angle":240},{"time":3.73,"angle":120},{"time":3.80,"angle":0},{"time":3.87,"angle":240},{"time":3.93,"angle":120},{"time":4,"angle":0},{"time":4.07,"angle":240},{"time":4.13,"angle":120},{"time":4.20,"angle":0},{"time":4.27,"angle":240},{"time":4.33,"angle":120},{"time":4.40,"angle":0},{"time":4.47,"angle":240},{"time":4.53,"angle":120},{"time":4.60,"angle":0},{"time":4.67,"angle":240},{"time":4.73,"angle":120},{"time":4.80,"angle":0},{"time":4.87,"angle":240},{"time":4.93,"angle":120},{"time":5,"angle":0},{"time":5.07,"angle":240},{"time":5.13,"angle":120},{"time":5.20,"angle":0},{"time":5.27,"angle":240},{"time":5.33,"angle":120},{"time":5.40,"angle":0},{"time":5.47,"angle":240},{"time":5.53,"angle":120},{"time":5.60,"angle":0},{"time":5.67,"angle":240},{"time":5.73,"angle":120},{"time":5.80,"angle":0},{"time":5.87,"angle":240},{"time":5.93,"angle":120},{"time":6,"angle":0},{"time":6.07,"angle":240},{"time":6.13,"angle":120},{"time":6.20,"angle":0},{"time":6.27,"angle":240},{"time":6.33,"angle":120},{"time":6.40,"angle":0},{"time":6.47,"angle":240},{"time":6.53,"angle":120},{"time":6.60,"angle":0},{"time":6.67,"angle":240},{"time":6.73,"angle":120},{"time":6.80,"angle":0},{"time":6.87,"angle":240},{"time":6.93,"angle":120},{"time":7,"angle":0},{"time":7.07,"angle":240},{"time":7.13,"angle":120},{"time":7.20,"angle":0},{"time":7.27,"angle":240},{"time":7.33,"angle":120},{"time":7.40,"angle":0},{"time":7.47,"angle":240},{"time":7.53,"angle":120},{"time":7.60,"angle":0},{"time":7.67,"angle":240},{"time":7.73,"angle":120},{"time":7.80,"angle":0},{"time":7.87,"angle":240},{"time":7.93,"angle":120},{"time":8,"angle":0},{"time":8.07,"angle":240},{"time":8.13,"angle":120},{"time":8.20,"angle":0},{"time":8.27,"angle":240},{"time":8.33,"angle":120},{"time":8.40,"angle":0},{"time":8.47,"angle":240},{"time":8.53,"angle":120},{"time":8.60,"angle":0},{"time":8.67,"angle":240},{"time":8.73,"angle":120},{"time":8.80,"angle":0},{"time":8.87,"angle":240},{"time":8.93,"angle":120},{"time":9,"angle":0},{"time":9.07,"angle":240},{"time":9.13,"angle":120},{"time":9.20,"angle":0},{"time":9.27,"angle":240},{"time":9.33,"angle":120},{"time":9.40,"angle":0},{"time":9.47,"angle":240},{"time":9.53,"angle":120},{"time":9.60,"angle":0},{"time":9.67,"angle":240},{"time":9.73,"angle":120},{"time":9.80,"angle":0},{"time":9.87,"angle":240},{"time":9.93,"angle":120},{"time":10,"angle":0},{"time":10.07,"angle":240},{"time":10.13,"angle":120},{"time":10.20,"angle":0},{"time":10.27,"angle":240},{"time":10.33,"angle":120},{"time":10.40,"angle":0},{"time":10.47,"angle":240},{"time":10.53,"angle":120},{"time":10.60,"angle":0},{"time":10.67,"angle":240},{"time":10.73,"angle":120},{"time":10.80,"angle":0},{"time":10.87,"angle":240},{"time":10.93,"angle":120},{"time":11,"angle":0},{"time":11.07,"angle":240},{"time":11.13,"angle":120},{"time":11.20,"angle":0},{"time":11.27,"angle":240},{"time":11.33,"angle":120},{"time":11.40,"angle":0},{"time":11.47,"angle":240},{"time":11.53,"angle":120},{"time":11.60,"angle":0},{"time":11.67,"angle":240},{"time":11.73,"angle":120},{"time":11.80,"angle":0},{"time":11.87,"angle":240},{"time":11.93,"angle":120},{"time":12,"angle":0}],"translate":[{"time":0,"x":0,"y":0,"curve":"stepped"},{"time":12,"x":0,"y":0}],"scale":[{"time":0,"x":1,"y":1,"curve":"stepped"},{"time":12,"x":1,"y":1}]},"bone7":{"rotate":[{"time":0,"angle":0,"curve":"stepped"},{"time":12,"angle":0}],"translate":[{"time":0,"x":-37.90,"y":0,"curve":[0.30060,0.22501,0.65116,0.61536]},{"time":2,"x":-12.76,"y":3.72,"curve":[0.37601,0.50549,0.74929,1]},{"time":4.93,"x":17.91,"y":-7.30,"curve":[0.25000,0,0.75000,1]},{"time":7.33,"x":-17.66,"y":-7.31,"curve":[0.28817,0,0.62758,0.37815]},{"time":12,"x":-37.90,"y":0}],"scale":[{"time":0,"x":0.96053,"y":0.96053,"curve":[0.25000,0,0.75000,1]},{"time":4,"x":1,"y":1,"curve":[0.25000,0,0.75000,1]},{"time":7.33,"x":0.96053,"y":0.96053,"curve":"stepped"},{"time":12,"x":0.96053,"y":0.96053}]},"root":{"rotate":[{"time":0,"angle":0,"curve":"stepped"},{"time":12,"angle":0}],"translate":[{"time":0,"x":0,"y":0,"curve":[0.27181,0,0.61913,0.40909]},{"time":0.83333,"x":-10.18,"y":-5.62,"curve":[0.31661,0.28143,0.66782,0.67025]},{"time":1.87,"x":-0.68734,"y":3.75,"curve":[0.38206,0.55446,0.74012,1]},{"time":3,"x":-19.96,"y":0,"curve":[0.26882,0,0.61828,0.41667]},{"time":3.90,"x":-3.82,"y":-3.75,"curve":[0.32161,0.29676,0.68046,0.70970]},{"time":5.13,"x":-6.63,"y":7.50,"curve":[0.38134,0.58716,0.72971,1]},{"time":6.20,"x":5.63,"y":3.75,"curve":[0.26740,0,0.61798,0.42056]},{"time":7.23,"x":-5.37,"y":-3.75,"curve":[0.32205,0.29849,0.67438,0.69051]},{"time":8.37,"x":0.80793,"y":1.88,"curve":[0.26603,0,0.61777,0.42453]},{"time":9.60,"x":13.57,"y":-7.50,"curve":[0.32528,0.30824,0.68277,0.71685]},{"time":10.57,"x":-3.82,"y":-1.88,"curve":[0.38087,0.59091,0.72819,1]},{"time":12,"x":0,"y":0}],"scale":[{"time":0,"x":1,"y":1,"curve":[0.25000,0,0.75000,1]},{"time":6,"x":1.03,"y":1.03,"curve":[0.25000,0,0.75000,1]},{"time":12,"x":1,"y":1}]}}},"START":{"slots":{"a1":{"color":[{"time":0,"color":"ffffff00","curve":"stepped"},{"time":0.66667,"color":"ffffff00"},{"time":1,"color":"ffffffff"},{"time":1.33,"color":"ffffff00"},{"time":1.67,"color":"ffffffff","curve":"stepped"},{"time":8,"color":"ffffffff"}]},"a2":{"color":[{"time":0,"color":"adadadff"},{"time":1.67,"color":"ffffffff"},{"time":2.33,"color":"ffffff00","curve":"stepped"},{"time":8,"color":"ffffff00"}]},"back2":{"color":[{"time":0,"color":"ffffffff","curve":"stepped"},{"time":1.33,"color":"ffffffff"},{"time":3,"color":"ffffff00"},{"time":6.67,"color":"ffffffff","curve":"stepped"},{"time":8,"color":"ffffffff"}]},"l1":{"color":[{"time":0,"color":"ffffffff"},{"time":0.33333,"color":"ffffff00","curve":"stepped"},{"time":0.66667,"color":"ffffff00"},{"time":1,"color":"ffffffff","curve":"stepped"},{"time":1.33,"color":"ffffffff"},{"time":1.67,"color":"ffffff00","curve":"stepped"},{"time":2.33,"color":"ffffff00"},{"time":2.67,"color":"ffffffff","curve":"stepped"},{"time":3,"color":"ffffffff"},{"time":3.33,"color":"ffffff00","curve":"stepped"},{"time":3.67,"color":"ffffff00"},{"time":4,"color":"ffffffff","curve":"stepped"},{"time":4.33,"color":"ffffffff"},{"time":4.67,"color":"ffffff00","curve":"stepped"},{"time":5.33,"color":"ffffff00"},{"time":5.67,"color":"ffffffff","curve":"stepped"},{"time":6,"color":"ffffffff"},{"time":6.33,"color":"ffffff00","curve":"stepped"},{"time":6.67,"color":"ffffff00"},{"time":7,"color":"ffffffff","curve":"stepped"},{"time":7.33,"color":"ffffffff"},{"time":7.67,"color":"ffffff00"},{"time":8,"color":"ffffffff"}]},"l2":{"color":[{"time":0,"color":"ffffff00","curve":"stepped"},{"time":0.33333,"color":"ffffff00"},{"time":0.96667,"color":"ffffffff","curve":"stepped"},{"time":1.80,"color":"ffffffff"},{"time":2.43,"color":"ffffff00","curve":"stepped"},{"time":2.87,"color":"ffffff00"},{"time":3.50,"color":"ffffffff","curve":"stepped"},{"time":4.33,"color":"ffffffff"},{"time":4.97,"color":"ffffff00","curve":"stepped"},{"time":5.43,"color":"ffffff00"},{"time":6.03,"color":"ffffffff","curve":"stepped"},{"time":6.87,"color":"ffffffff"},{"time":7.50,"color":"ffffff00","curve":"stepped"},{"time":7.83,"color":"ffffff00","curve":"stepped"},{"time":8,"color":"ffffff00"}]},"l3":{"color":[{"time":0,"color":"ffffff00"},{"time":0.63333,"color":"ffffffff","curve":"stepped"},{"time":1.47,"color":"ffffffff"},{"time":2.10,"color":"ffffff00","curve":"stepped"},{"time":3.77,"color":"ffffff00"},{"time":4.37,"color":"ffffffff","curve":"stepped"},{"time":5.20,"color":"ffffffff"},{"time":5.83,"color":"ffffff00","curve":"stepped"},{"time":7.50,"color":"ffffff00","curve":"stepped"},{"time":8,"color":"ffffff00"}]},"l4":{"color":[{"time":0,"color":"ffffff00","curve":"stepped"},{"time":0.33333,"color":"ffffff00"},{"time":0.66667,"color":"ffffffff","curve":"stepped"},{"time":1.13,"color":"ffffffff"},{"time":1.47,"color":"ffffff00","curve":"stepped"},{"time":2.33,"color":"ffffff00"},{"time":2.67,"color":"ffffffff","curve":"stepped"},{"time":3.13,"color":"ffffffff"},{"time":3.47,"color":"ffffff00","curve":"stepped"},{"time":4.13,"color":"ffffff00"},{"time":4.47,"color":"ffffffff","curve":"stepped"},{"time":4.93,"color":"ffffffff"},{"time":5.27,"color":"ffffff00","curve":"stepped"},{"time":6.03,"color":"ffffff00"},{"time":6.37,"color":"ffffffff","curve":"stepped"},{"time":6.83,"color":"ffffffff"},{"time":7.17,"color":"ffffff00","curve":"stepped"},{"time":7.50,"color":"ffffff00","curve":"stepped"},{"time":7.83,"color":"ffffff00","curve":"stepped"},{"time":8,"color":"ffffff00"}]},"l5":{"color":[{"time":0,"color":"ffffffff"},{"time":0.46667,"color":"ffffff00","curve":"stepped"},{"time":0.96667,"color":"ffffff00"},{"time":1.43,"color":"ffffffff","curve":"stepped"},{"time":1.93,"color":"ffffffff"},{"time":2.40,"color":"ffffff00","curve":"stepped"},{"time":3.37,"color":"ffffff00"},{"time":3.83,"color":"ffffffff","curve":"stepped"},{"time":4.30,"color":"ffffffff"},{"time":4.80,"color":"ffffff00","curve":"stepped"},{"time":5.27,"color":"ffffff00"},{"time":5.77,"color":"ffffffff","curve":"stepped"},{"time":6.23,"color":"ffffffff"},{"time":6.70,"color":"ffffff00","curve":"stepped"},{"time":7.67,"color":"ffffff00"},{"time":8,"color":"ffffffff"}]},"screen":{"color":[{"time":0,"color":"ffffff40"},{"time":0.83333,"color":"ffffff83","curve":"stepped"},{"time":1.67,"color":"ffffff83"},{"time":2.50,"color":"ffffff40","curve":"stepped"},{"time":3.13,"color":"ffffff40"},{"time":3.97,"color":"ffffff83","curve":"stepped"},{"time":4.80,"color":"ffffff83"},{"time":5.63,"color":"ffffff40","curve":"stepped"},{"time":6,"color":"ffffff40"},{"time":6.83,"color":"ffffff83","curve":"stepped"},{"time":7.67,"color":"ffffff83"},{"time":8,"color":"ffffff40"}]}},"bones":{"bone":{"rotate":[{"time":8,"angle":0}],"translate":[{"time":0,"x":0,"y":0,"curve":[0.25000,0,0.75000,1]},{"time":6,"x":-6.68,"y":8.91,"curve":[0.25000,0,0.75000,1]},{"time":8,"x":0,"y":0}],"scale":[{"time":0,"x":1,"y":1,"curve":[0.25000,0,0.75000,1]},{"time":6,"x":1.01,"y":1.01,"curve":[0.25000,0,0.75000,1]},{"time":8,"x":1,"y":1}]},"bone2":{"rotate":[{"time":0,"angle":0.09366,"curve":[0.30791,0.25225,0.65819,0.63964]},{"time":2,"angle":0.35149,"curve":[0.37931,0.52632,0.74608,1]},{"time":4.67,"angle":0.61299,"curve":[0.25000,0,0.75000,1]},{"time":8,"angle":0.09366}],"translate":[{"time":0,"x":0,"y":-7.77,"curve":[0.38235,0.57143,0.73529,1]},{"time":2,"x":-18.40,"y":-0.11291,"curve":[0.25000,0,0.75000,1]},{"time":8,"x":0,"y":-7.77}],"scale":[{"time":0,"x":1.01,"y":1.01,"curve":[0.38235,0.57143,0.73529,1]},{"time":2,"x":1,"y":1},{"time":8,"x":1.01,"y":1.01}]},"bone3":{"rotate":[{"time":8,"angle":0}],"translate":[{"time":8,"x":0,"y":0}],"scale":[{"time":8,"x":1,"y":1}]},"bone4":{"rotate":[{"time":0,"angle":0},{"time":0.06667,"angle":240},{"time":0.13333,"angle":120},{"time":0.20000,"angle":0},{"time":0.26667,"angle":240},{"time":0.33333,"angle":120},{"time":0.40000,"angle":0},{"time":0.46667,"angle":240},{"time":0.53333,"angle":120},{"time":0.60000,"angle":0},{"time":0.66667,"angle":240},{"time":0.73333,"angle":120},{"time":0.80000,"angle":0},{"time":0.86667,"angle":240},{"time":0.93333,"angle":120},{"time":1,"angle":0},{"time":1.07,"angle":240},{"time":1.13,"angle":120},{"time":1.20,"angle":0},{"time":1.27,"angle":240},{"time":1.33,"angle":120},{"time":1.40,"angle":0},{"time":1.47,"angle":240},{"time":1.53,"angle":120},{"time":1.60,"angle":0},{"time":1.67,"angle":240},{"time":1.73,"angle":120},{"time":1.80,"angle":0},{"time":1.87,"angle":240},{"time":1.93,"angle":120},{"time":2,"angle":0},{"time":2.07,"angle":240},{"time":2.13,"angle":120},{"time":2.20,"angle":0},{"time":2.27,"angle":240},{"time":2.33,"angle":120},{"time":2.40,"angle":0},{"time":2.47,"angle":240},{"time":2.53,"angle":120},{"time":2.60,"angle":0},{"time":2.67,"angle":240},{"time":2.73,"angle":120},{"time":2.80,"angle":0},{"time":2.87,"angle":240},{"time":2.93,"angle":120},{"time":3,"angle":0},{"time":3.07,"angle":240},{"time":3.13,"angle":120},{"time":3.20,"angle":0},{"time":3.27,"angle":240},{"time":3.33,"angle":120},{"time":3.40,"angle":0},{"time":3.47,"angle":240},{"time":3.53,"angle":120},{"time":3.60,"angle":0},{"time":3.67,"angle":240},{"time":3.73,"angle":120},{"time":3.80,"angle":0},{"time":3.87,"angle":240},{"time":3.93,"angle":120},{"time":4,"angle":0},{"time":4.07,"angle":240},{"time":4.13,"angle":120},{"time":4.20,"angle":0},{"time":4.27,"angle":240},{"time":4.33,"angle":120},{"time":4.40,"angle":0},{"time":4.47,"angle":240},{"time":4.53,"angle":120},{"time":4.60,"angle":0},{"time":4.67,"angle":240},{"time":4.73,"angle":120},{"time":4.80,"angle":0},{"time":4.87,"angle":240},{"time":4.93,"angle":120},{"time":5,"angle":0},{"time":5.07,"angle":240},{"time":5.13,"angle":120},{"time":5.20,"angle":0},{"time":5.27,"angle":240},{"time":5.33,"angle":120},{"time":5.40,"angle":0},{"time":5.47,"angle":240},{"time":5.53,"angle":120},{"time":5.60,"angle":0},{"time":5.67,"angle":240},{"time":5.73,"angle":120},{"time":5.80,"angle":0},{"time":5.87,"angle":240},{"time":5.93,"angle":120},{"time":6,"angle":0},{"time":6.07,"angle":240},{"time":6.13,"angle":120},{"time":6.20,"angle":0},{"time":6.27,"angle":240},{"time":6.33,"angle":120},{"time":6.40,"angle":0},{"time":6.47,"angle":240},{"time":6.53,"angle":120},{"time":6.60,"angle":0},{"time":6.67,"angle":240},{"time":6.73,"angle":120},{"time":6.80,"angle":0},{"time":6.87,"angle":240},{"time":6.93,"angle":120},{"time":7,"angle":0},{"time":7.07,"angle":240},{"time":7.13,"angle":120},{"time":7.20,"angle":0},{"time":7.27,"angle":240},{"time":7.33,"angle":120},{"time":7.40,"angle":0},{"time":7.47,"angle":240},{"time":7.53,"angle":120},{"time":7.60,"angle":0},{"time":7.67,"angle":240},{"time":7.73,"angle":120},{"time":7.80,"angle":0},{"time":7.87,"angle":240},{"time":7.93,"angle":120},{"time":8,"angle":0}],"translate":[{"time":8,"x":0,"y":0}],"scale":[{"time":8,"x":1,"y":1}]},"bone5":{"rotate":[{"time":8,"angle":0}],"translate":[{"time":8,"x":0,"y":0}],"scale":[{"time":8,"x":1,"y":1}]},"bone6":{"rotate":[{"time":0,"angle":0},{"time":0.06667,"angle":240},{"time":0.13333,"angle":120},{"time":0.20000,"angle":0},{"time":0.26667,"angle":240},{"time":0.33333,"angle":120},{"time":0.40000,"angle":0},{"time":0.46667,"angle":240},{"time":0.53333,"angle":120},{"time":0.60000,"angle":0},{"time":0.66667,"angle":240},{"time":0.73333,"angle":120},{"time":0.80000,"angle":0},{"time":0.86667,"angle":240},{"time":0.93333,"angle":120},{"time":1,"angle":0},{"time":1.07,"angle":240},{"time":1.13,"angle":120},{"time":1.20,"angle":0},{"time":1.27,"angle":240},{"time":1.33,"angle":120},{"time":1.40,"angle":0},{"time":1.47,"angle":240},{"time":1.53,"angle":120},{"time":1.60,"angle":0},{"time":1.67,"angle":240},{"time":1.73,"angle":120},{"time":1.80,"angle":0},{"time":1.87,"angle":240},{"time":1.93,"angle":120},{"time":2,"angle":0},{"time":2.07,"angle":240},{"time":2.13,"angle":120},{"time":2.20,"angle":0},{"time":2.27,"angle":240},{"time":2.33,"angle":120},{"time":2.40,"angle":0},{"time":2.47,"angle":240},{"time":2.53,"angle":120},{"time":2.60,"angle":0},{"time":2.67,"angle":240},{"time":2.73,"angle":120},{"time":2.80,"angle":0},{"time":2.87,"angle":240},{"time":2.93,"angle":120},{"time":3,"angle":0},{"time":3.07,"angle":240},{"time":3.13,"angle":120},{"time":3.20,"angle":0},{"time":3.27,"angle":240},{"time":3.33,"angle":120},{"time":3.40,"angle":0},{"time":3.47,"angle":240},{"time":3.53,"angle":120},{"time":3.60,"angle":0},{"time":3.67,"angle":240},{"time":3.73,"angle":120},{"time":3.80,"angle":0},{"time":3.87,"angle":240},{"time":3.93,"angle":120},{"time":4,"angle":0},{"time":4.07,"angle":240},{"time":4.13,"angle":120},{"time":4.20,"angle":0},{"time":4.27,"angle":240},{"time":4.33,"angle":120},{"time":4.40,"angle":0},{"time":4.47,"angle":240},{"time":4.53,"angle":120},{"time":4.60,"angle":0},{"time":4.67,"angle":240},{"time":4.73,"angle":120},{"time":4.80,"angle":0},{"time":4.87,"angle":240},{"time":4.93,"angle":120},{"time":5,"angle":0},{"time":5.07,"angle":240},{"time":5.13,"angle":120},{"time":5.20,"angle":0},{"time":5.27,"angle":240},{"time":5.33,"angle":120},{"time":5.40,"angle":0},{"time":5.47,"angle":240},{"time":5.53,"angle":120},{"time":5.60,"angle":0},{"time":5.67,"angle":240},{"time":5.73,"angle":120},{"time":5.80,"angle":0},{"time":5.87,"angle":240},{"time":5.93,"angle":120},{"time":6,"angle":0},{"time":6.07,"angle":240},{"time":6.13,"angle":120},{"time":6.20,"angle":0},{"time":6.27,"angle":240},{"time":6.33,"angle":120},{"time":6.40,"angle":0},{"time":6.47,"angle":240},{"time":6.53,"angle":120},{"time":6.60,"angle":0},{"time":6.67,"angle":240},{"time":6.73,"angle":120},{"time":6.80,"angle":0},{"time":6.87,"angle":240},{"time":6.93,"angle":120},{"time":7,"angle":0},{"time":7.07,"angle":240},{"time":7.13,"angle":120},{"time":7.20,"angle":0},{"time":7.27,"angle":240},{"time":7.33,"angle":120},{"time":7.40,"angle":0},{"time":7.47,"angle":240},{"time":7.53,"angle":120},{"time":7.60,"angle":0},{"time":7.67,"angle":240},{"time":7.73,"angle":120},{"time":7.80,"angle":0},{"time":7.87,"angle":240},{"time":7.93,"angle":120},{"time":8,"angle":0}],"translate":[{"time":8,"x":0,"y":0}],"scale":[{"time":8,"x":1,"y":1}]},"bone7":{"rotate":[{"time":8,"angle":0}],"translate":[{"time":0,"x":-37.90,"y":0,"curve":[0.30060,0.22501,0.65116,0.61536]},{"time":2,"x":-16.48,"y":0,"curve":[0.37601,0.50549,0.74929,1]},{"time":4.93,"x":8.78,"y":0,"curve":[0.25000,0,0.75000,1]},{"time":8,"x":-37.90,"y":0}],"scale":[{"time":0,"x":1.09,"y":1.09},{"time":4,"x":1,"y":1,"curve":[0.25000,0,0.75000,1]},{"time":8,"x":0.96053,"y":0.96053}]},"root":{"rotate":[{"time":0,"angle":-3.42,"curve":[0.25000,0,0.75000,1]},{"time":6,"angle":0,"curve":"stepped"},{"time":8,"angle":0}],"translate":[{"time":0,"x":0,"y":0,"curve":[0.28028,0,0.62284,0.39130]},{"time":0.10000,"x":-1.88,"y":0,"curve":[0.32899,0.31703,0.66250,0.65104]},{"time":0.23333,"x":-12.82,"y":-10,"curve":[0.33021,0.32286,0.66372,0.65677]},{"time":0.36667,"x":-13.86,"y":10,"curve":[0.33131,0.32699,0.66482,0.66085]},{"time":0.50000,"x":-1.88,"y":0,"curve":[0.32899,0.31703,0.66250,0.65104]},{"time":0.63333,"x":-12.82,"y":-10,"curve":[0.33021,0.32286,0.66372,0.65677]},{"time":0.76667,"x":-13.86,"y":10,"curve":[0.33131,0.32699,0.66482,0.66085]},{"time":0.90000,"x":7.66,"y":10,"curve":[0.32962,0.32024,0.66313,0.65420]},{"time":1.03,"x":6.67,"y":-10,"curve":[0.33078,0.32506,0.66428,0.65895]},{"time":1.17,"x":5.60,"y":0,"curve":[0.33333,0.33332,0.66666,0.66665]},{"time":1.43,"x":10.42,"y":4.96,"curve":[0.33333,0.33332,0.66666,0.66665]},{"time":1.70,"x":0.34606,"y":0,"curve":[0.33330,0.33322,0.66663,0.66656]},{"time":2.03,"x":-13.26,"y":-4.18,"curve":[0.33333,0.33331,0.66666,0.66664]},{"time":2.57,"x":-6.88,"y":0,"curve":[0.33329,0.33319,0.66662,0.66652]},{"time":3.40,"x":-5.33,"y":-10.44,"curve":[0.31307,0.24788,0.64894,0.59190]},{"time":4.13,"x":-4.10,"y":-8.35,"curve":[0.32888,0.31979,0.66444,0.65989]},{"time":5.20,"x":0,"y":0,"curve":[0.25000,0,0.75000,1]},{"time":6.40,"x":-5.33,"y":-10.44,"curve":[0.31307,0.24788,0.64894,0.59190]},{"time":7.47,"x":-0.96714,"y":-6.78,"curve":[0.32888,0.31979,0.66444,0.65989]},{"time":8,"x":0,"y":0}],"scale":[{"time":0,"x":2.73,"y":2.73,"curve":[0.24427,0,0.70229,0.80000]},{"time":1.70,"x":1.36,"y":1.36,"curve":[0.36449,0.63636,0.70093,1]},{"time":8,"x":1,"y":1}]}}}}}